README.rst
setup.py
Pymk.egg-info/PKG-INFO
Pymk.egg-info/SOURCES.txt
Pymk.egg-info/dependency_links.txt
Pymk.egg-info/entry_points.txt
Pymk.egg-info/requires.txt
Pymk.egg-info/top_level.txt
pymk/__init__.py
pymk/dependency.py
pymk/download.py
pymk/error.py
pymk/graph.py
pymk/recipe.py
pymk/script.py
pymk/task.py
pymk/extra/__init__.py
pymk/extra/cmd.py
pymk/extra/findfiles.py
pymk/extra/template.py
pymk/extra/touch.py
pymk/tests/__init__.py
pymk/tests/base.py
pymk/tests/dependency.py
pymk/tests/error.py
pymk/tests/recipe.py
pymk/tests/script.py
pymk/tests/task.py
pymk/tests/extra/__init__.py
pymk/tests/extra/cmd.py
pymk/tests/extra/findfiles.py
pymk/tests/extra/template.py
pymk/tests/extra/touch.py