Metadata-Version: 1.0
Name: Pymk
Version: 0.4.1
Summary: Make like program, which reads python script as makefile.
Home-page: UNKNOWN
Author: Dominik "Socek" Długajczyk
Author-email: msocek@gmail.com
License: UNKNOWN
Platform: UNKNOWN
